<?xml version="1.0" encoding="utf-8" ?>
<dwsync>
<file name="cmap.php" server="ftp.petroecol.com.br/public_html/" local="132712840886829876" remote="132536844000000000" Dst="0" />
<file name="glyf.php" server="ftp.petroecol.com.br/public_html/" local="132712840887178623" remote="132536844000000000" Dst="0" />
<file name="head.php" server="ftp.petroecol.com.br/public_html/" local="132712840887535542" remote="132536844000000000" Dst="0" />
<file name="hhea.php" server="ftp.petroecol.com.br/public_html/" local="132712840887645390" remote="132536844000000000" Dst="0" />
<file name="hmtx.php" server="ftp.petroecol.com.br/public_html/" local="132712840887804949" remote="132536844000000000" Dst="0" />
<file name="kern.php" server="ftp.petroecol.com.br/public_html/" local="132712840888190474" remote="132536844000000000" Dst="0" />
<file name="loca.php" server="ftp.petroecol.com.br/public_html/" local="132712840888350672" remote="132536844000000000" Dst="0" />
<file name="maxp.php" server="ftp.petroecol.com.br/public_html/" local="132712840888320793" remote="132536844000000000" Dst="0" />
<file name="name.php" server="ftp.petroecol.com.br/public_html/" local="132712840888799433" remote="132536844000000000" Dst="0" />
<file name="nameRecord.php" server="ftp.petroecol.com.br/public_html/" local="132712840888948540" remote="132536844000000000" Dst="0" />
<file name="os2.php" server="ftp.petroecol.com.br/public_html/" local="132712840889231202" remote="132536844000000000" Dst="0" />
<file name="post.php" server="ftp.petroecol.com.br/public_html/" local="132712840889691303" remote="132536844000000000" Dst="0" />
</dwsync>